{"kind":"Notebook","sha256":"e4eb357f70ba7f52a7c9165b7a99664510a0cf128f0d0bc306f7c8244287f937","slug":"hadleyvolleyballstats","location":"/HadleyVolleyballStats.ipynb","dependencies":[],"frontmatter":{"github":"https://github.com/charlottegoebel/Volleyball-Data-Analysis","keywords":[],"exports":[{"format":"ipynb","filename":"HadleyVolleyballStats.ipynb","url":"/HadleyVolleyballStat-b9d195c76b3daa80309ff3162b2a04d7.ipynb"}]},"mdast":{"type":"root","children":[{"type":"block","children":[{"type":"code","lang":"python","executable":true,"value":"import pandas as pd\nimport matplotlib.pyplot as plt\nimport numpy as np","key":"Z4Fc0DAJnT"},{"type":"output","id":"ab93q6q4mc9Edn6LqGRSH","data":[],"key":"irCfmlLhPx"}],"data":{"type":"notebook-code"},"key":"X8wJNyquZn"},{"type":"block","children":[{"type":"paragraph","position":{"start":{"line":1,"column":1},"end":{"line":1,"column":1}},"children":[{"type":"text","value":"22 Games Total","position":{"start":{"line":1,"column":1},"end":{"line":1,"column":1}},"key":"P5nXwsyiOg"}],"key":"OkArS25yXs"}],"data":{"type":"notebook-content"},"key":"jYrROotkJY"},{"type":"block","children":[{"type":"paragraph","position":{"start":{"line":1,"column":1},"end":{"line":8,"column":1}},"children":[{"type":"strong","position":{"start":{"line":1,"column":1},"end":{"line":1,"column":1}},"children":[{"type":"text","value":"Name:","position":{"start":{"line":1,"column":1},"end":{"line":1,"column":1}},"key":"gxAEFqVZnR"}],"key":"wx5IgQw28T"},{"type":"text","value":" Player Name\n","position":{"start":{"line":1,"column":1},"end":{"line":1,"column":1}},"key":"dm1DZZdl29"},{"type":"strong","position":{"start":{"line":1,"column":1},"end":{"line":1,"column":1}},"children":[{"type":"text","value":"SP:","position":{"start":{"line":1,"column":1},"end":{"line":1,"column":1}},"key":"vqgNSEge9M"}],"key":"TQnzogxKut"},{"type":"text","value":" Sets Played\n","position":{"start":{"line":1,"column":1},"end":{"line":1,"column":1}},"key":"FkSnnsjdJX"},{"type":"strong","position":{"start":{"line":1,"column":1},"end":{"line":1,"column":1}},"children":[{"type":"text","value":"K:","position":{"start":{"line":1,"column":1},"end":{"line":1,"column":1}},"key":"GHtP7Oyfxd"}],"key":"ysUcsVMWr6"},{"type":"text","value":" Kills\n","position":{"start":{"line":1,"column":1},"end":{"line":1,"column":1}},"key":"wNKFdtbcHw"},{"type":"strong","position":{"start":{"line":1,"column":1},"end":{"line":1,"column":1}},"children":[{"type":"text","value":"K/S:","position":{"start":{"line":1,"column":1},"end":{"line":1,"column":1}},"key":"rUwHMiDooC"}],"key":"BkmrVxVCAo"},{"type":"text","value":" Average Number of Kills Per Set\n","position":{"start":{"line":1,"column":1},"end":{"line":1,"column":1}},"key":"jsbFGt3tBS"},{"type":"strong","position":{"start":{"line":1,"column":1},"end":{"line":1,"column":1}},"children":[{"type":"text","value":"Kill %:","position":{"start":{"line":1,"column":1},"end":{"line":1,"column":1}},"key":"T4L8w0thT4"}],"key":"xHFliwQkz2"},{"type":"text","value":" Kill Percentage\n","position":{"start":{"line":1,"column":1},"end":{"line":1,"column":1}},"key":"fRd2bOjudA"},{"type":"strong","position":{"start":{"line":1,"column":1},"end":{"line":1,"column":1}},"children":[{"type":"text","value":"Att:","position":{"start":{"line":1,"column":1},"end":{"line":1,"column":1}},"key":"wDYbs7q97a"}],"key":"pbHC5FE9Ah"},{"type":"text","value":" Attack Attempts\n","position":{"start":{"line":1,"column":1},"end":{"line":1,"column":1}},"key":"lkKSTJwmVU"},{"type":"strong","position":{"start":{"line":1,"column":1},"end":{"line":1,"column":1}},"children":[{"type":"text","value":"E:","position":{"start":{"line":1,"column":1},"end":{"line":1,"column":1}},"key":"FYlmAA14Iu"}],"key":"DoMzJmFTKt"},{"type":"text","value":" Attack Errors\n","position":{"start":{"line":1,"column":1},"end":{"line":1,"column":1}},"key":"gFXPNhslRa"},{"type":"strong","position":{"start":{"line":1,"column":1},"end":{"line":1,"column":1}},"children":[{"type":"text","value":"Hit %:","position":{"start":{"line":1,"column":1},"end":{"line":1,"column":1}},"key":"uaDOVYm0pb"}],"key":"ldZhiQIDWU"},{"type":"text","value":" Hitting Percentage","position":{"start":{"line":1,"column":1},"end":{"line":1,"column":1}},"key":"yWRNL5NDpF"}],"key":"PgJyuDChfe"}],"data":{"type":"notebook-content"},"key":"vHUpe4fIiR"},{"type":"block","children":[{"type":"code","lang":"python","executable":true,"value":"attacking_full = pd.read_csv(\"Attacking - Sheet1.csv\")\nattacking = attacking_full[[\"K\", \"Att\", \"E\"]]\nattacking","key":"GqUgrXe4JU"},{"type":"output","id":"ay39v4xwlotKahuVbmh-b","data":[{"output_type":"execute_result","execution_count":32,"metadata":{},"data":{"text/html":{"content":"<div>\n<style scoped>\n    .dataframe tbody tr th:only-of-type {\n        vertical-align: middle;\n    }\n\n    .dataframe tbody tr th {\n        vertical-align: top;\n    }\n\n    .dataframe thead th {\n        text-align: right;\n    }\n</style>\n<table border=\"1\" class=\"dataframe\">\n  <thead>\n    <tr style=\"text-align: right;\">\n      <th></th>\n      <th>K</th>\n      <th>Att</th>\n      <th>E</th>\n    </tr>\n  </thead>\n  <tbody>\n    <tr>\n      <th>0</th>\n      <td>156</td>\n      <td>616</td>\n      <td>87</td>\n    </tr>\n    <tr>\n      <th>1</th>\n      <td>5</td>\n      <td>74</td>\n      <td>12</td>\n    </tr>\n    <tr>\n      <th>2</th>\n      <td>83</td>\n      <td>260</td>\n      <td>32</td>\n    </tr>\n    <tr>\n      <th>3</th>\n      <td>90</td>\n      <td>386</td>\n      <td>67</td>\n    </tr>\n    <tr>\n      <th>4</th>\n      <td>2</td>\n      <td>27</td>\n      <td>7</td>\n    </tr>\n    <tr>\n      <th>5</th>\n      <td>61</td>\n      <td>179</td>\n      <td>39</td>\n    </tr>\n    <tr>\n      <th>6</th>\n      <td>140</td>\n      <td>489</td>\n      <td>84</td>\n    </tr>\n    <tr>\n      <th>7</th>\n      <td>2</td>\n      <td>14</td>\n      <td>3</td>\n    </tr>\n    <tr>\n      <th>8</th>\n      <td>6</td>\n      <td>45</td>\n      <td>6</td>\n    </tr>\n    <tr>\n      <th>9</th>\n      <td>2</td>\n      <td>7</td>\n      <td>1</td>\n    </tr>\n    <tr>\n      <th>10</th>\n      <td>128</td>\n      <td>443</td>\n      <td>58</td>\n    </tr>\n  </tbody>\n</table>\n</div>","content_type":"text/html"},"text/plain":{"content":"      K  Att   E\n0   156  616  87\n1     5   74  12\n2    83  260  32\n3    90  386  67\n4     2   27   7\n5    61  179  39\n6   140  489  84\n7     2   14   3\n8     6   45   6\n9     2    7   1\n10  128  443  58","content_type":"text/plain"}}}],"key":"kPSsqrk81i"}],"data":{"type":"notebook-code"},"key":"t8AQYaZNb4"},{"type":"block","children":[{"type":"code","lang":"python","executable":true,"value":"success = (attacking[\"K\"] - attacking[\"E\"])\nhitting_percentage = (successfull_hits/attacking[\"Att\"]*100)\nhitting_percentage","key":"BYQjea6DwY"},{"type":"output","id":"gFjUcQeiYjv3m6Enwn7v8","data":[{"output_type":"execute_result","execution_count":13,"metadata":{},"data":{"text/plain":{"content":"0     11.201299\n1     -9.459459\n2     19.615385\n3      5.958549\n4    -18.518519\n5     12.290503\n6     11.451943\n7     -7.142857\n8      0.000000\n9     14.285714\n10    15.801354\ndtype: float64","content_type":"text/plain"}}}],"key":"WuVEKEaj9x"}],"data":{"type":"notebook-code"},"key":"C452M0Xaik"},{"type":"block","children":[{"type":"paragraph","position":{"start":{"line":1,"column":1},"end":{"line":9,"column":1}},"children":[{"type":"strong","position":{"start":{"line":1,"column":1},"end":{"line":1,"column":1}},"children":[{"type":"text","value":"Name:","position":{"start":{"line":1,"column":1},"end":{"line":1,"column":1}},"key":"wckpMSL9gp"}],"key":"idULBzMLiP"},{"type":"text","value":" Player Name\n","position":{"start":{"line":1,"column":1},"end":{"line":1,"column":1}},"key":"OlJ6evpg0i"},{"type":"strong","position":{"start":{"line":1,"column":1},"end":{"line":1,"column":1}},"children":[{"type":"text","value":"SP:","position":{"start":{"line":1,"column":1},"end":{"line":1,"column":1}},"key":"FuRA0DtG1v"}],"key":"M97ni56ONI"},{"type":"text","value":" Sets Played\n","position":{"start":{"line":1,"column":1},"end":{"line":1,"column":1}},"key":"l82w4suGHJ"},{"type":"strong","position":{"start":{"line":1,"column":1},"end":{"line":1,"column":1}},"children":[{"type":"text","value":"A:","position":{"start":{"line":1,"column":1},"end":{"line":1,"column":1}},"key":"sWxWrCvN3x"}],"key":"ejvKrgsPpT"},{"type":"text","value":" Aces\n","position":{"start":{"line":1,"column":1},"end":{"line":1,"column":1}},"key":"O8FeRg67gk"},{"type":"strong","position":{"start":{"line":1,"column":1},"end":{"line":1,"column":1}},"children":[{"type":"text","value":"A/S:","position":{"start":{"line":1,"column":1},"end":{"line":1,"column":1}},"key":"sdZSgkS0T9"}],"key":"owmXlMUSUo"},{"type":"text","value":" Average Number of Aces Per Set\n","position":{"start":{"line":1,"column":1},"end":{"line":1,"column":1}},"key":"XX7tgxobht"},{"type":"strong","position":{"start":{"line":1,"column":1},"end":{"line":1,"column":1}},"children":[{"type":"text","value":"Ace %:","position":{"start":{"line":1,"column":1},"end":{"line":1,"column":1}},"key":"MmccmKttbT"}],"key":"PQFnrfg4Rk"},{"type":"text","value":" Ace Percentage - (Total Aces/Total SA)\n","position":{"start":{"line":1,"column":1},"end":{"line":1,"column":1}},"key":"u11BpDh2JK"},{"type":"strong","position":{"start":{"line":1,"column":1},"end":{"line":1,"column":1}},"children":[{"type":"text","value":"SA:","position":{"start":{"line":1,"column":1},"end":{"line":1,"column":1}},"key":"qzbYBYhJrI"}],"key":"TDXEQsRiDb"},{"type":"text","value":" Service Attempts\n","position":{"start":{"line":1,"column":1},"end":{"line":1,"column":1}},"key":"dHlWOwQ7f5"},{"type":"strong","position":{"start":{"line":1,"column":1},"end":{"line":1,"column":1}},"children":[{"type":"text","value":"SE:","position":{"start":{"line":1,"column":1},"end":{"line":1,"column":1}},"key":"khqkLfd4UB"}],"key":"Fk1O9txrin"},{"type":"text","value":" Service Errors\n","position":{"start":{"line":1,"column":1},"end":{"line":1,"column":1}},"key":"ybIOyOUlxc"},{"type":"strong","position":{"start":{"line":1,"column":1},"end":{"line":1,"column":1}},"children":[{"type":"text","value":"Serv %:","position":{"start":{"line":1,"column":1},"end":{"line":1,"column":1}},"key":"UEK4cvRcAR"}],"key":"b8c5BlU75U"},{"type":"text","value":" Serving Percentage - ((SA-SE)/SA)\n","position":{"start":{"line":1,"column":1},"end":{"line":1,"column":1}},"key":"IV3dbpfSv9"},{"type":"strong","position":{"start":{"line":1,"column":1},"end":{"line":1,"column":1}},"children":[{"type":"text","value":"PTS:","position":{"start":{"line":1,"column":1},"end":{"line":1,"column":1}},"key":"lw1ip9z3NS"}],"key":"i0ZRpB7paK"},{"type":"text","value":" Rotation Points - (# of points scored while this person was serving)","position":{"start":{"line":1,"column":1},"end":{"line":1,"column":1}},"key":"hHQLEGuNKo"}],"key":"tJwIwxnqg6"}],"data":{"type":"notebook-content"},"key":"udiWGjqofQ"},{"type":"block","children":[{"type":"code","lang":"python","executable":true,"value":"serving_full = pd.read_csv(\"Serving - Sheet1.csv\")\nserving = serving_full[[\"SA\", \"A\", \"SE\"]]\nserving","key":"mVsZy5bNUi"},{"type":"output","id":"nPjacyCXb7X2xG1dkekRq","data":[{"output_type":"execute_result","execution_count":31,"metadata":{},"data":{"text/html":{"content":"<div>\n<style scoped>\n    .dataframe tbody tr th:only-of-type {\n        vertical-align: middle;\n    }\n\n    .dataframe tbody tr th {\n        vertical-align: top;\n    }\n\n    .dataframe thead th {\n        text-align: right;\n    }\n</style>\n<table border=\"1\" class=\"dataframe\">\n  <thead>\n    <tr style=\"text-align: right;\">\n      <th></th>\n      <th>SA</th>\n      <th>A</th>\n      <th>SE</th>\n    </tr>\n  </thead>\n  <tbody>\n    <tr>\n      <th>0</th>\n      <td>332</td>\n      <td>54</td>\n      <td>31</td>\n    </tr>\n    <tr>\n      <th>1</th>\n      <td>291</td>\n      <td>49</td>\n      <td>16</td>\n    </tr>\n    <tr>\n      <th>2</th>\n      <td>191</td>\n      <td>16</td>\n      <td>15</td>\n    </tr>\n    <tr>\n      <th>3</th>\n      <td>47</td>\n      <td>5</td>\n      <td>9</td>\n    </tr>\n    <tr>\n      <th>4</th>\n      <td>222</td>\n      <td>47</td>\n      <td>30</td>\n    </tr>\n    <tr>\n      <th>5</th>\n      <td>33</td>\n      <td>3</td>\n      <td>5</td>\n    </tr>\n    <tr>\n      <th>6</th>\n      <td>273</td>\n      <td>27</td>\n      <td>9</td>\n    </tr>\n    <tr>\n      <th>7</th>\n      <td>223</td>\n      <td>43</td>\n      <td>38</td>\n    </tr>\n  </tbody>\n</table>\n</div>","content_type":"text/html"},"text/plain":{"content":"    SA   A  SE\n0  332  54  31\n1  291  49  16\n2  191  16  15\n3   47   5   9\n4  222  47  30\n5   33   3   5\n6  273  27   9\n7  223  43  38","content_type":"text/plain"}}}],"key":"x74ZpI5nTk"}],"data":{"type":"notebook-code"},"key":"QE9oILH9sc"},{"type":"block","children":[{"type":"code","lang":"python","executable":true,"value":"success2 = (serving[\"SA\"] - serving[\"SE\"])\nserving_percentage = (success2/serving[\"SA\"]*100)\nserving_percentage","key":"XXW1A5sOTn"},{"type":"output","id":"bVYDCd0K--SQQ_7cXDarc","data":[{"output_type":"execute_result","execution_count":30,"metadata":{},"data":{"text/plain":{"content":"0    90.662651\n1    94.501718\n2    92.146597\n3    80.851064\n4    86.486486\n5    84.848485\n6    96.703297\n7    82.959641\ndtype: float64","content_type":"text/plain"}}}],"key":"kDoQsvhe9X"}],"data":{"type":"notebook-code"},"key":"ylPWbxbedV"},{"type":"block","children":[{"type":"paragraph","position":{"start":{"line":1,"column":1},"end":{"line":8,"column":1}},"children":[{"type":"strong","position":{"start":{"line":1,"column":1},"end":{"line":1,"column":1}},"children":[{"type":"text","value":"Name:","position":{"start":{"line":1,"column":1},"end":{"line":1,"column":1}},"key":"v08yjUJcxc"}],"key":"e4gyUj6cjO"},{"type":"text","value":" Player Name\n","position":{"start":{"line":1,"column":1},"end":{"line":1,"column":1}},"key":"uq93gsovB3"},{"type":"strong","position":{"start":{"line":1,"column":1},"end":{"line":1,"column":1}},"children":[{"type":"text","value":"SP:","position":{"start":{"line":1,"column":1},"end":{"line":1,"column":1}},"key":"u34VNoO2FY"}],"key":"EHPdjED47R"},{"type":"text","value":" Sets Played\n","position":{"start":{"line":1,"column":1},"end":{"line":1,"column":1}},"key":"o2tgIWeLjc"},{"type":"strong","position":{"start":{"line":1,"column":1},"end":{"line":1,"column":1}},"children":[{"type":"text","value":"BS:","position":{"start":{"line":1,"column":1},"end":{"line":1,"column":1}},"key":"D4kfp9JFhA"}],"key":"g4aIpLroOP"},{"type":"text","value":" Total Blocks By Player Solo\n","position":{"start":{"line":1,"column":1},"end":{"line":1,"column":1}},"key":"L6hulQOPQm"},{"type":"strong","position":{"start":{"line":1,"column":1},"end":{"line":1,"column":1}},"children":[{"type":"text","value":"BA:","position":{"start":{"line":1,"column":1},"end":{"line":1,"column":1}},"key":"UDUTppO9xA"}],"key":"VvPkkM26p7"},{"type":"text","value":" Total Blocks By Player Assisted\n","position":{"start":{"line":1,"column":1},"end":{"line":1,"column":1}},"key":"VnK9VIrhG7"},{"type":"strong","position":{"start":{"line":1,"column":1},"end":{"line":1,"column":1}},"children":[{"type":"text","value":"Tot Blks:","position":{"start":{"line":1,"column":1},"end":{"line":1,"column":1}},"key":"K40ewmy3n8"}],"key":"CFVjvKTkau"},{"type":"text","value":" Total Blocks By Player Solo & Assisted\n","position":{"start":{"line":1,"column":1},"end":{"line":1,"column":1}},"key":"ovCk5w5REf"},{"type":"strong","position":{"start":{"line":1,"column":1},"end":{"line":1,"column":1}},"children":[{"type":"text","value":"B/S:","position":{"start":{"line":1,"column":1},"end":{"line":1,"column":1}},"key":"PfsJ32yoek"}],"key":"uVXJISIWuo"},{"type":"text","value":" Average Number of Blocks Per Set\n","position":{"start":{"line":1,"column":1},"end":{"line":1,"column":1}},"key":"g9MOEPFD71"},{"type":"strong","position":{"start":{"line":1,"column":1},"end":{"line":1,"column":1}},"children":[{"type":"text","value":"B/M:","position":{"start":{"line":1,"column":1},"end":{"line":1,"column":1}},"key":"RP7OcXRfAb"}],"key":"GQgCbIGvAT"},{"type":"text","value":" Average Number of Blocks Per Match\n","position":{"start":{"line":1,"column":1},"end":{"line":1,"column":1}},"key":"tfvEIf5sEe"},{"type":"strong","position":{"start":{"line":1,"column":1},"end":{"line":1,"column":1}},"children":[{"type":"text","value":"BE:","position":{"start":{"line":1,"column":1},"end":{"line":1,"column":1}},"key":"GYROaLUrQX"}],"key":"IRLiqzJP6E"},{"type":"text","value":" Blocking Errors","position":{"start":{"line":1,"column":1},"end":{"line":1,"column":1}},"key":"RSyLng83xE"}],"key":"b12XDKayHe"}],"data":{"type":"notebook-content"},"key":"HAkMUp6Ax0"},{"type":"block","children":[{"type":"code","lang":"python","executable":true,"value":"blocking_full = pd.read_csv(\"Blocking - Sheet1.csv\")\nblocking = blocking_full[[\"BS\", \"BA\", \"Tot Blks\", \"BE\"]]\nblocking","key":"HoJk9yYvV5"},{"type":"output","id":"8jyDkypak61rzukECnjax","data":[{"output_type":"execute_result","execution_count":36,"metadata":{},"data":{"text/html":{"content":"<div>\n<style scoped>\n    .dataframe tbody tr th:only-of-type {\n        vertical-align: middle;\n    }\n\n    .dataframe tbody tr th {\n        vertical-align: top;\n    }\n\n    .dataframe thead th {\n        text-align: right;\n    }\n</style>\n<table border=\"1\" class=\"dataframe\">\n  <thead>\n    <tr style=\"text-align: right;\">\n      <th></th>\n      <th>BS</th>\n      <th>BA</th>\n      <th>Tot Blks</th>\n      <th>BE</th>\n    </tr>\n  </thead>\n  <tbody>\n    <tr>\n      <th>0</th>\n      <td>1</td>\n      <td>3</td>\n      <td>4</td>\n      <td>2</td>\n    </tr>\n    <tr>\n      <th>1</th>\n      <td>15</td>\n      <td>15</td>\n      <td>30</td>\n      <td>9</td>\n    </tr>\n    <tr>\n      <th>2</th>\n      <td>3</td>\n      <td>5</td>\n      <td>8</td>\n      <td>4</td>\n    </tr>\n    <tr>\n      <th>3</th>\n      <td>18</td>\n      <td>13</td>\n      <td>31</td>\n      <td>20</td>\n    </tr>\n    <tr>\n      <th>4</th>\n      <td>0</td>\n      <td>4</td>\n      <td>4</td>\n      <td>6</td>\n    </tr>\n    <tr>\n      <th>5</th>\n      <td>0</td>\n      <td>1</td>\n      <td>1</td>\n      <td>0</td>\n    </tr>\n    <tr>\n      <th>6</th>\n      <td>16</td>\n      <td>15</td>\n      <td>31</td>\n      <td>13</td>\n    </tr>\n  </tbody>\n</table>\n</div>","content_type":"text/html"},"text/plain":{"content":"   BS  BA  Tot Blks  BE\n0   1   3         4   2\n1  15  15        30   9\n2   3   5         8   4\n3  18  13        31  20\n4   0   4         4   6\n5   0   1         1   0\n6  16  15        31  13","content_type":"text/plain"}}}],"key":"xulm3PKayb"}],"data":{"type":"notebook-code"},"key":"jHOD6dpM2S"},{"type":"block","children":[{"type":"code","lang":"python","executable":true,"value":"success3 = (blocking[\"Tot Blks\"]-blocking[\"BE\"])\nblocking_percentage = (success3/blocking[\"Tot Blks\"])\nblocking_percentage","key":"jpNhXLXlUv"},{"type":"output","id":"9VuMIyZ5eacoC5KKS4NzG","data":[{"output_type":"execute_result","execution_count":37,"metadata":{},"data":{"text/plain":{"content":"0    0.500000\n1    0.700000\n2    0.500000\n3    0.354839\n4   -0.500000\n5    1.000000\n6    0.580645\ndtype: float64","content_type":"text/plain"}}}],"key":"itNI01Yx2l"}],"data":{"type":"notebook-code"},"key":"Fuy5EObSv5"}],"key":"uK7Nf1zNVe"},"references":{"cite":{"order":[],"data":{}}}}